ast_to_xml.py
ast_to_xml-0.2.4.dist-info/LICENSE
ast_to_xml-0.2.4.dist-info/WHEEL
ast_to_xml-0.2.4.dist-info/METADATA
ast_to_xml-0.2.4.dist-info/RECORD
